server/__init__.py
server/server.py
server/logs/__init__.py
server/logs/client_log_config.py
server/logs/server_log_config.py
server/modules/__init__.py
server/modules/decos.py
server/modules/descriptors.py
server/modules/functions.py
server/modules/metaclasses.py
server/modules/variables.py
server/server/__init__.py
server/server/config_window.py
server/server/core.py
server/server/main_window.py
server/server/registration.py
server/server/remove_user.py
server/server/server_database.py
server/server/statistic_window.py
server/unit_tests/__init__.py
mess_server_project-1.0.0.dist-info/METADATA
mess_server_project-1.0.0.dist-info/WHEEL
mess_server_project-1.0.0.dist-info/top_level.txt
mess_server_project-1.0.0.dist-info/RECORD
