Metadata-Version: 2.1
Name: mess-server-project
Version: 1.0.0
Summary: mess_server_project
Home-page: UNKNOWN
Author: Shalyapin Artem
Author-email: shalyapin.artyom@yandex.ru
License: UNKNOWN
Platform: UNKNOWN
Requires-Dist: PyQt5
Requires-Dist: sqlalchemy
Requires-Dist: pycryptodome
Requires-Dist: pycryptodomex
